[
  {
    "id": "ivanti-itsm-administrator",
    "name": "Ivanti ITSM Administrator",
    "group": "Service Management",
    "summary": "Owns configuration, forms, workflows, communications, dashboards, and day-to-day platform administration for Ivanti Neurons for ITSM.",
    "moduleIds": [
      "ivanti-neurons-for-itsm",
      "incident-management",
      "problem-management",
      "change-management",
      "service-request-management",
      "knowledge-management",
      "reporting-and-dashboards",
      "ivanti-neurons-ipaas"
    ],
    "skills": [
      "configuration design",
      "workflow thinking",
      "reporting",
      "operational governance",
      "user support"
    ],
    "topicIds": [
      "approvals",
      "authentication-patterns",
      "business-objects",
      "change-governance",
      "dashboards-and-kpis",
      "data-mapping",
      "email-templates",
      "error-handling-and-retries",
      "escalations",
      "forms-and-layouts",
      "incident-lifecycle",
      "knowledge-lifecycle",
      "problem-lifecycle",
      "quick-actions",
      "relationships",
      "request-fulfillment",
      "rest-api-basics",
      "saved-searches",
      "validations",
      "workflows"
    ],
    "codingIds": [
      "approval-routing-logic",
      "auth-token-flow-review",
      "business-object-extension-plan",
      "change-risk-and-approval-design",
      "dashboard-kpi-design",
      "data-mapping-strategy",
      "email-template-dynamic-fields",
      "escalation-trigger-design",
      "form-layout-design-review",
      "incident-priority-and-routing",
      "knowledge-feedback-loop",
      "notification-automation-with-saved-searches",
      "problem-trend-analysis",
      "quick-action-design-pattern",
      "relationship-impact-walk-through",
      "request-fulfillment-task-design",
      "rest-integration-walk-through",
      "retry-and-backoff-patterns",
      "validation-logic-design",
      "workflow-exception-handling"
    ],
    "useCaseIds": [
      "asset-refresh-planning",
      "change-approval-and-scheduling",
      "custom-object-design-review",
      "customer-response-reactivation",
      "escalation-schedule-tuning",
      "external-approval-sync",
      "knowledge-deflection-for-support",
      "multi-step-request-approvals",
      "persona-based-form-redesign",
      "pilot-based-patch-rollout",
      "problem-review-and-corrective-action",
      "quick-action-notification-pack",
      "relationship-driven-task-model",
      "scheduled-report-push-to-external-endpoint",
      "validation-guardrail-rollout",
      "weekly-open-incident-summary",
      "workspace-shift-left-triage"
    ],
    "trickyIds": [
      "approval-vs-fulfillment-task",
      "authn-vs-authz-in-integrations",
      "catalog-request-vs-fulfillment-task",
      "dashboard-vs-report",
      "escalation-vs-notification",
      "incident-vs-problem",
      "incident-vs-service-request",
      "ipaas-connector-vs-custom-integration",
      "knowledge-article-vs-workaround",
      "lookup-vs-parent-child-relationship",
      "mapping-vs-transformation",
      "object-extension-vs-new-object",
      "problem-vs-known-error",
      "quick-action-vs-workflow",
      "retry-vs-replay",
      "saved-search-vs-dashboard",
      "single-form-vs-role-specific-layouts",
      "standard-vs-normal-change",
      "template-content-vs-recipient-logic",
      "ui-required-vs-business-validation",
      "workflow-vs-state-driven-routing"
    ],
    "priority": "Core",
    "whatInterviewersUsuallyAsk": [
      "How do you design multi-step approvals?",
      "Why does authentication design matter?",
      "What is a business object?",
      "How do you assess change risk?",
      "How do you route approvals by request type?",
      "How do you store credentials safely?"
    ],
    "answerFramework": [
      "Start with what the role owns day to day.",
      "Mention the highest-priority modules you would focus on first.",
      "Name the topics interviewers usually probe for this role.",
      "Close with one implementation example or support scenario."
    ],
    "studyOrder": [
      "Core topics first",
      "Then coding or automation questions",
      "Then use cases",
      "Finish with tricky distinctions and quiz review"
    ]
  },
  {
    "id": "ivanti-itsm-developer",
    "name": "Ivanti ITSM Developer",
    "group": "Service Management",
    "summary": "Builds advanced automations, integrations, validation logic, and extensibility patterns across the service platform.",
    "moduleIds": [
      "ivanti-neurons-for-itsm",
      "incident-management",
      "change-management",
      "service-request-management",
      "ivanti-neurons-ipaas",
      "ivanti-neurons-platform"
    ],
    "skills": [
      "integration design",
      "automation logic",
      "data modeling",
      "troubleshooting",
      "secure API design"
    ],
    "topicIds": [
      "approvals",
      "authentication-patterns",
      "business-objects",
      "change-governance",
      "data-mapping",
      "email-templates",
      "error-handling-and-retries",
      "escalations",
      "forms-and-layouts",
      "incident-lifecycle",
      "quick-actions",
      "relationships",
      "request-fulfillment",
      "rest-api-basics",
      "validations",
      "workflows"
    ],
    "codingIds": [
      "approval-routing-logic",
      "auth-token-flow-review",
      "business-object-extension-plan",
      "change-risk-and-approval-design",
      "data-mapping-strategy",
      "email-template-dynamic-fields",
      "escalation-trigger-design",
      "form-layout-design-review",
      "incident-priority-and-routing",
      "quick-action-design-pattern",
      "relationship-impact-walk-through",
      "request-fulfillment-task-design",
      "rest-integration-walk-through",
      "retry-and-backoff-patterns",
      "validation-logic-design",
      "workflow-exception-handling"
    ],
    "useCaseIds": [
      "change-approval-and-scheduling",
      "custom-object-design-review",
      "customer-response-reactivation",
      "escalation-schedule-tuning",
      "external-approval-sync",
      "knowledge-deflection-for-support",
      "multi-step-request-approvals",
      "persona-based-form-redesign",
      "platform-cross-workflow-automation",
      "quick-action-notification-pack",
      "relationship-driven-task-model",
      "scheduled-report-push-to-external-endpoint",
      "validation-guardrail-rollout",
      "weekly-open-incident-summary",
      "workspace-shift-left-triage"
    ],
    "trickyIds": [
      "approval-vs-fulfillment-task",
      "authn-vs-authz-in-integrations",
      "catalog-request-vs-fulfillment-task",
      "escalation-vs-notification",
      "incident-vs-service-request",
      "ipaas-connector-vs-custom-integration",
      "lookup-vs-parent-child-relationship",
      "mapping-vs-transformation",
      "object-extension-vs-new-object",
      "quick-action-vs-workflow",
      "retry-vs-replay",
      "single-form-vs-role-specific-layouts",
      "standard-vs-normal-change",
      "template-content-vs-recipient-logic",
      "ui-required-vs-business-validation",
      "workflow-vs-state-driven-routing"
    ],
    "priority": "Core",
    "whatInterviewersUsuallyAsk": [
      "How do you design multi-step approvals?",
      "Why does authentication design matter?",
      "What is a business object?",
      "How do you assess change risk?",
      "How do you route approvals by request type?",
      "How do you store credentials safely?"
    ],
    "answerFramework": [
      "Start with what the role owns day to day.",
      "Mention the highest-priority modules you would focus on first.",
      "Name the topics interviewers usually probe for this role.",
      "Close with one implementation example or support scenario."
    ],
    "studyOrder": [
      "Core topics first",
      "Then coding or automation questions",
      "Then use cases",
      "Finish with tricky distinctions and quiz review"
    ]
  },
  {
    "id": "ivanti-uem-engineer",
    "name": "Ivanti UEM Engineer",
    "group": "Endpoint",
    "summary": "Supports unified endpoint management across inventory, compliance, policy, software, and lifecycle management.",
    "moduleIds": [
      "ivanti-neurons-for-uem",
      "ivanti-endpoint-manager",
      "patch-management",
      "software-distribution",
      "compliance-and-policy",
      "ivanti-neurons-for-discovery"
    ],
    "skills": [
      "device governance",
      "policy control",
      "distribution planning",
      "remediation",
      "operational reporting"
    ],
    "topicIds": [
      "compliance-rules",
      "device-groups-and-targeting",
      "discovery-and-inventory",
      "endpoint-troubleshooting",
      "patch-rings",
      "software-distribution-jobs"
    ],
    "codingIds": [
      "compliance-remediation-design",
      "discovery-scan-and-reconciliation",
      "endpoint-targeting-strategy",
      "patch-ring-rollout-design",
      "software-deployment-failure-triage",
      "software-distribution-wave-design",
      "uem-policy-baseline-review"
    ],
    "useCaseIds": [
      "byod-enrollment-program",
      "discovery-policy-rollout",
      "discovery-reconciliation-improvement",
      "managed-mobile-app-rollout",
      "non-compliant-device-response",
      "pilot-based-patch-rollout",
      "software-distribution-validation",
      "targeted-software-rollout",
      "uem-device-lifecycle-control"
    ],
    "trickyIds": [
      "agent-issue-vs-policy-issue",
      "compliance-state-vs-remediation-action",
      "discovery-vs-itam-record",
      "distribution-vs-app-distribution",
      "patch-ring-vs-broad-rollout",
      "uem-vs-endpoint-manager"
    ],
    "priority": "Core",
    "whatInterviewersUsuallyAsk": [
      "What is a compliance rule?",
      "Why are device groups important?",
      "Why is discovery important?",
      "How do you troubleshoot failed jobs?",
      "How do you respond to a non-compliant device?",
      "How do you describe discovery at a high level?"
    ],
    "answerFramework": [
      "Start with what the role owns day to day.",
      "Mention the highest-priority modules you would focus on first.",
      "Name the topics interviewers usually probe for this role.",
      "Close with one implementation example or support scenario."
    ],
    "studyOrder": [
      "Core topics first",
      "Then coding or automation questions",
      "Then use cases",
      "Finish with tricky distinctions and quiz review"
    ]
  },
  {
    "id": "ivanti-endpoint-manager-engineer",
    "name": "Ivanti Endpoint Manager Engineer",
    "group": "Endpoint",
    "summary": "Handles package deployment, targeting, inventory, and endpoint operations using Endpoint Manager.",
    "moduleIds": [
      "ivanti-endpoint-manager",
      "software-distribution",
      "patch-management",
      "ivanti-neurons-for-discovery"
    ],
    "skills": [
      "deployment design",
      "endpoint troubleshooting",
      "targeting strategy",
      "job monitoring",
      "inventory validation"
    ],
    "topicIds": [
      "device-groups-and-targeting",
      "discovery-and-inventory",
      "endpoint-troubleshooting",
      "patch-rings",
      "software-distribution-jobs"
    ],
    "codingIds": [
      "discovery-scan-and-reconciliation",
      "endpoint-targeting-strategy",
      "patch-ring-rollout-design",
      "software-deployment-failure-triage",
      "software-distribution-wave-design",
      "uem-policy-baseline-review"
    ],
    "useCaseIds": [
      "discovery-policy-rollout",
      "discovery-reconciliation-improvement",
      "pilot-based-patch-rollout",
      "software-distribution-validation",
      "targeted-software-rollout",
      "uem-device-lifecycle-control"
    ],
    "trickyIds": [
      "agent-issue-vs-policy-issue",
      "discovery-vs-itam-record",
      "distribution-vs-app-distribution",
      "patch-ring-vs-broad-rollout",
      "uem-vs-endpoint-manager"
    ],
    "priority": "Important",
    "whatInterviewersUsuallyAsk": [
      "Why are device groups important?",
      "Why is discovery important?",
      "How do you troubleshoot failed jobs?",
      "Why use patch rings?",
      "How do you describe discovery at a high level?",
      "How do you design targeting groups?"
    ],
    "answerFramework": [
      "Start with what the role owns day to day.",
      "Mention the highest-priority modules you would focus on first.",
      "Name the topics interviewers usually probe for this role.",
      "Close with one implementation example or support scenario."
    ],
    "studyOrder": [
      "Core topics first",
      "Then coding or automation questions",
      "Then use cases",
      "Finish with tricky distinctions and quiz review"
    ]
  },
  {
    "id": "ivanti-patch-management-engineer",
    "name": "Ivanti Patch Management Engineer",
    "group": "Endpoint",
    "summary": "Designs patch rings, pilot waves, compliance monitoring, and exception handling strategies.",
    "moduleIds": [
      "patch-management",
      "ivanti-endpoint-manager",
      "ivanti-neurons-for-uem",
      "reporting-and-dashboards"
    ],
    "skills": [
      "risk-aware rollout",
      "patch governance",
      "exception management",
      "compliance analysis",
      "stakeholder communication"
    ],
    "topicIds": [
      "dashboards-and-kpis",
      "device-groups-and-targeting",
      "endpoint-troubleshooting",
      "patch-rings",
      "saved-searches"
    ],
    "codingIds": [
      "dashboard-kpi-design",
      "endpoint-targeting-strategy",
      "notification-automation-with-saved-searches",
      "patch-ring-rollout-design",
      "software-deployment-failure-triage",
      "uem-policy-baseline-review"
    ],
    "useCaseIds": [
      "asset-refresh-planning",
      "escalation-schedule-tuning",
      "pilot-based-patch-rollout",
      "problem-review-and-corrective-action",
      "quick-action-notification-pack",
      "scheduled-report-push-to-external-endpoint",
      "software-distribution-validation",
      "targeted-software-rollout",
      "uem-device-lifecycle-control",
      "validation-guardrail-rollout",
      "weekly-open-incident-summary"
    ],
    "trickyIds": [
      "agent-issue-vs-policy-issue",
      "dashboard-vs-report",
      "patch-ring-vs-broad-rollout",
      "saved-search-vs-dashboard",
      "uem-vs-endpoint-manager"
    ],
    "priority": "Important",
    "whatInterviewersUsuallyAsk": [
      "Which KPIs matter?",
      "Why are device groups important?",
      "How do you troubleshoot failed jobs?",
      "Why use patch rings?",
      "How do you choose KPIs?",
      "How do you design targeting groups?"
    ],
    "answerFramework": [
      "Start with what the role owns day to day.",
      "Mention the highest-priority modules you would focus on first.",
      "Name the topics interviewers usually probe for this role.",
      "Close with one implementation example or support scenario."
    ],
    "studyOrder": [
      "Core topics first",
      "Then coding or automation questions",
      "Then use cases",
      "Finish with tricky distinctions and quiz review"
    ]
  },
  {
    "id": "ivanti-mdm-engineer",
    "name": "Ivanti MDM Engineer",
    "group": "Mobility",
    "summary": "Manages enrollment, compliance, app rollout, ownership models, and managed device controls.",
    "moduleIds": [
      "ivanti-neurons-for-mdm",
      "compliance-and-policy",
      "mobile-app-distribution",
      "reporting-and-dashboards"
    ],
    "skills": [
      "enrollment strategy",
      "policy governance",
      "mobile rollout planning",
      "security baselines",
      "user experience"
    ],
    "topicIds": [
      "compliance-rules",
      "dashboards-and-kpis",
      "enrollment",
      "mobile-app-deployment",
      "ownership-models",
      "saved-searches"
    ],
    "codingIds": [
      "compliance-remediation-design",
      "dashboard-kpi-design",
      "enrollment-troubleshooting",
      "mobile-app-rollout-planning",
      "notification-automation-with-saved-searches",
      "ownership-model-policy-mapping"
    ],
    "useCaseIds": [
      "asset-refresh-planning",
      "byod-enrollment-program",
      "escalation-schedule-tuning",
      "managed-mobile-app-rollout",
      "non-compliant-device-response",
      "pilot-based-patch-rollout",
      "problem-review-and-corrective-action",
      "quick-action-notification-pack",
      "scheduled-report-push-to-external-endpoint",
      "validation-guardrail-rollout",
      "weekly-open-incident-summary"
    ],
    "trickyIds": [
      "byod-vs-corporate-owned",
      "compliance-state-vs-remediation-action",
      "dashboard-vs-report",
      "device-enrolled-vs-device-compliant",
      "required-vs-available-mobile-app",
      "saved-search-vs-dashboard"
    ],
    "priority": "Core",
    "whatInterviewersUsuallyAsk": [
      "What is a compliance rule?",
      "Which KPIs matter?",
      "How do you explain enrollment?",
      "How do you plan app rollout?",
      "How do you respond to a non-compliant device?",
      "How do you choose KPIs?"
    ],
    "answerFramework": [
      "Start with what the role owns day to day.",
      "Mention the highest-priority modules you would focus on first.",
      "Name the topics interviewers usually probe for this role.",
      "Close with one implementation example or support scenario."
    ],
    "studyOrder": [
      "Core topics first",
      "Then coding or automation questions",
      "Then use cases",
      "Finish with tricky distinctions and quiz review"
    ]
  },
  {
    "id": "ivanti-itam-engineer",
    "name": "Ivanti ITAM Engineer",
    "group": "Asset",
    "summary": "Focuses on lifecycle tracking, normalization, inventory alignment, and asset reporting.",
    "moduleIds": [
      "ivanti-neurons-for-itam",
      "ivanti-neurons-for-discovery",
      "reporting-and-dashboards",
      "ivanti-neurons-ipaas"
    ],
    "skills": [
      "lifecycle management",
      "inventory trust",
      "reconciliation",
      "reporting",
      "data quality"
    ],
    "topicIds": [
      "asset-lifecycle",
      "authentication-patterns",
      "dashboards-and-kpis",
      "data-mapping",
      "discovery-and-inventory",
      "error-handling-and-retries",
      "normalization-and-reconciliation",
      "rest-api-basics",
      "saved-searches"
    ],
    "codingIds": [
      "asset-lifecycle-state-model",
      "asset-reconciliation-approach",
      "auth-token-flow-review",
      "dashboard-kpi-design",
      "data-mapping-strategy",
      "discovery-scan-and-reconciliation",
      "notification-automation-with-saved-searches",
      "rest-integration-walk-through",
      "retry-and-backoff-patterns"
    ],
    "useCaseIds": [
      "asset-refresh-planning",
      "discovery-policy-rollout",
      "discovery-reconciliation-improvement",
      "escalation-schedule-tuning",
      "external-approval-sync",
      "pilot-based-patch-rollout",
      "problem-review-and-corrective-action",
      "quick-action-notification-pack",
      "scheduled-report-push-to-external-endpoint",
      "validation-guardrail-rollout",
      "weekly-open-incident-summary"
    ],
    "trickyIds": [
      "asset-record-vs-discovered-record",
      "authn-vs-authz-in-integrations",
      "dashboard-vs-report",
      "discovery-vs-itam-record",
      "ipaas-connector-vs-custom-integration",
      "itam-vs-discovery",
      "mapping-vs-transformation",
      "retry-vs-replay",
      "saved-search-vs-dashboard"
    ],
    "priority": "Core",
    "whatInterviewersUsuallyAsk": [
      "How do you explain lifecycle?",
      "Why does authentication design matter?",
      "Which KPIs matter?",
      "What matters in mapping?",
      "What lifecycle states matter most?",
      "How do you improve reconciliation quality?"
    ],
    "answerFramework": [
      "Start with what the role owns day to day.",
      "Mention the highest-priority modules you would focus on first.",
      "Name the topics interviewers usually probe for this role.",
      "Close with one implementation example or support scenario."
    ],
    "studyOrder": [
      "Core topics first",
      "Then coding or automation questions",
      "Then use cases",
      "Finish with tricky distinctions and quiz review"
    ]
  },
  {
    "id": "ivanti-discovery-engineer",
    "name": "Ivanti Discovery Engineer",
    "group": "Asset",
    "summary": "Builds and supports discovery, connectors, normalized inventory, and reconciliation-ready visibility.",
    "moduleIds": [
      "ivanti-neurons-for-discovery",
      "ivanti-neurons-for-itam",
      "reporting-and-dashboards"
    ],
    "skills": [
      "connector strategy",
      "normalization",
      "inventory visibility",
      "reconciliation",
      "source-of-truth thinking"
    ],
    "topicIds": [
      "asset-lifecycle",
      "dashboards-and-kpis",
      "discovery-and-inventory",
      "normalization-and-reconciliation",
      "saved-searches"
    ],
    "codingIds": [
      "asset-lifecycle-state-model",
      "asset-reconciliation-approach",
      "dashboard-kpi-design",
      "discovery-scan-and-reconciliation",
      "notification-automation-with-saved-searches"
    ],
    "useCaseIds": [
      "asset-refresh-planning",
      "discovery-policy-rollout",
      "discovery-reconciliation-improvement",
      "escalation-schedule-tuning",
      "pilot-based-patch-rollout",
      "problem-review-and-corrective-action",
      "quick-action-notification-pack",
      "scheduled-report-push-to-external-endpoint",
      "validation-guardrail-rollout",
      "weekly-open-incident-summary"
    ],
    "trickyIds": [
      "asset-record-vs-discovered-record",
      "dashboard-vs-report",
      "discovery-vs-itam-record",
      "itam-vs-discovery",
      "saved-search-vs-dashboard"
    ],
    "priority": "Advanced",
    "whatInterviewersUsuallyAsk": [
      "How do you explain lifecycle?",
      "Which KPIs matter?",
      "Why is discovery important?",
      "What is normalization?",
      "What lifecycle states matter most?",
      "How do you improve reconciliation quality?"
    ],
    "answerFramework": [
      "Start with what the role owns day to day.",
      "Mention the highest-priority modules you would focus on first.",
      "Name the topics interviewers usually probe for this role.",
      "Close with one implementation example or support scenario."
    ],
    "studyOrder": [
      "Core topics first",
      "Then coding or automation questions",
      "Then use cases",
      "Finish with tricky distinctions and quiz review"
    ]
  },
  {
    "id": "ivanti-grc-analyst",
    "name": "Ivanti GRC Analyst",
    "group": "Governance",
    "summary": "Supports controls, risks, authority documents, assessments, and corrective-action workflows.",
    "moduleIds": [
      "ivanti-neurons-for-grc",
      "reporting-and-dashboards",
      "ivanti-neurons-ipaas"
    ],
    "skills": [
      "control mapping",
      "risk thinking",
      "assessment design",
      "auditability",
      "corrective action tracking"
    ],
    "topicIds": [
      "authentication-patterns",
      "authority-documents-and-citations",
      "controls-and-risks",
      "dashboards-and-kpis",
      "data-mapping",
      "error-handling-and-retries",
      "rest-api-basics",
      "saved-searches"
    ],
    "codingIds": [
      "auth-token-flow-review",
      "authority-document-structure",
      "dashboard-kpi-design",
      "data-mapping-strategy",
      "grc-control-mapping-approach",
      "notification-automation-with-saved-searches",
      "rest-integration-walk-through",
      "retry-and-backoff-patterns"
    ],
    "useCaseIds": [
      "asset-refresh-planning",
      "control-assessment-cycle",
      "escalation-schedule-tuning",
      "external-approval-sync",
      "grc-authority-import-and-control-map",
      "pilot-based-patch-rollout",
      "problem-review-and-corrective-action",
      "quick-action-notification-pack",
      "scheduled-report-push-to-external-endpoint",
      "validation-guardrail-rollout",
      "weekly-open-incident-summary"
    ],
    "trickyIds": [
      "authn-vs-authz-in-integrations",
      "citation-vs-control",
      "control-vs-risk",
      "dashboard-vs-report",
      "ipaas-connector-vs-custom-integration",
      "mapping-vs-transformation",
      "retry-vs-replay",
      "saved-search-vs-dashboard"
    ],
    "priority": "Advanced",
    "whatInterviewersUsuallyAsk": [
      "Why does authentication design matter?",
      "Why do citations matter?",
      "How do controls reduce risk?",
      "Which KPIs matter?",
      "How do you store credentials safely?",
      "How do citations connect requirements to controls?"
    ],
    "answerFramework": [
      "Start with what the role owns day to day.",
      "Mention the highest-priority modules you would focus on first.",
      "Name the topics interviewers usually probe for this role.",
      "Close with one implementation example or support scenario."
    ],
    "studyOrder": [
      "Core topics first",
      "Then coding or automation questions",
      "Then use cases",
      "Finish with tricky distinctions and quiz review"
    ]
  },
  {
    "id": "ivanti-integration-architect",
    "name": "Ivanti Integration Architect",
    "group": "Integrations",
    "summary": "Designs secure, maintainable, and scalable integrations between Ivanti and external systems.",
    "moduleIds": [
      "ivanti-neurons-ipaas",
      "ivanti-neurons-for-itsm",
      "ivanti-neurons-for-itam",
      "ivanti-neurons-for-grc",
      "ivanti-neurons-platform"
    ],
    "skills": [
      "API architecture",
      "authentication",
      "mapping",
      "retry strategy",
      "governance"
    ],
    "topicIds": [
      "asset-lifecycle",
      "authentication-patterns",
      "authority-documents-and-citations",
      "business-objects",
      "controls-and-risks",
      "data-mapping",
      "email-templates",
      "error-handling-and-retries",
      "forms-and-layouts",
      "normalization-and-reconciliation",
      "quick-actions",
      "relationships",
      "rest-api-basics",
      "validations",
      "workflows"
    ],
    "codingIds": [
      "asset-lifecycle-state-model",
      "asset-reconciliation-approach",
      "auth-token-flow-review",
      "authority-document-structure",
      "business-object-extension-plan",
      "data-mapping-strategy",
      "email-template-dynamic-fields",
      "form-layout-design-review",
      "grc-control-mapping-approach",
      "quick-action-design-pattern",
      "relationship-impact-walk-through",
      "rest-integration-walk-through",
      "retry-and-backoff-patterns",
      "validation-logic-design",
      "workflow-exception-handling"
    ],
    "useCaseIds": [
      "asset-refresh-planning",
      "change-approval-and-scheduling",
      "control-assessment-cycle",
      "custom-object-design-review",
      "customer-response-reactivation",
      "discovery-policy-rollout",
      "discovery-reconciliation-improvement",
      "external-approval-sync",
      "grc-authority-import-and-control-map",
      "multi-step-request-approvals",
      "persona-based-form-redesign",
      "platform-cross-workflow-automation",
      "quick-action-notification-pack",
      "relationship-driven-task-model",
      "scheduled-report-push-to-external-endpoint",
      "validation-guardrail-rollout",
      "weekly-open-incident-summary"
    ],
    "trickyIds": [
      "asset-record-vs-discovered-record",
      "authn-vs-authz-in-integrations",
      "citation-vs-control",
      "control-vs-risk",
      "ipaas-connector-vs-custom-integration",
      "itam-vs-discovery",
      "lookup-vs-parent-child-relationship",
      "mapping-vs-transformation",
      "object-extension-vs-new-object",
      "quick-action-vs-workflow",
      "retry-vs-replay",
      "single-form-vs-role-specific-layouts",
      "template-content-vs-recipient-logic",
      "ui-required-vs-business-validation",
      "workflow-vs-state-driven-routing"
    ],
    "priority": "Core",
    "whatInterviewersUsuallyAsk": [
      "How do you explain lifecycle?",
      "Why does authentication design matter?",
      "Why do citations matter?",
      "What is a business object?",
      "What lifecycle states matter most?",
      "How do you improve reconciliation quality?"
    ],
    "answerFramework": [
      "Start with what the role owns day to day.",
      "Mention the highest-priority modules you would focus on first.",
      "Name the topics interviewers usually probe for this role.",
      "Close with one implementation example or support scenario."
    ],
    "studyOrder": [
      "Core topics first",
      "Then coding or automation questions",
      "Then use cases",
      "Finish with tricky distinctions and quiz review"
    ]
  },
  {
    "id": "ivanti-workspace-analyst",
    "name": "Ivanti Workspace Analyst",
    "group": "Experience",
    "summary": "Uses Workspace context and quick actions to accelerate triage and resolution.",
    "moduleIds": [
      "ivanti-neurons-workspace",
      "ivanti-neurons-for-itsm",
      "incident-management",
      "reporting-and-dashboards"
    ],
    "skills": [
      "triage efficiency",
      "workspace actions",
      "shift-left operations",
      "contextual troubleshooting",
      "knowledge reuse"
    ],
    "topicIds": [
      "business-objects",
      "dashboards-and-kpis",
      "email-templates",
      "forms-and-layouts",
      "incident-lifecycle",
      "quick-actions",
      "relationships",
      "saved-searches",
      "validations",
      "workflows",
      "workspace-triage"
    ],
    "codingIds": [
      "business-object-extension-plan",
      "dashboard-kpi-design",
      "email-template-dynamic-fields",
      "form-layout-design-review",
      "incident-priority-and-routing",
      "notification-automation-with-saved-searches",
      "quick-action-design-pattern",
      "relationship-impact-walk-through",
      "validation-logic-design",
      "workflow-exception-handling",
      "workspace-first-line-remediation",
      "workspace-quick-action-thinking"
    ],
    "useCaseIds": [
      "asset-refresh-planning",
      "change-approval-and-scheduling",
      "custom-object-design-review",
      "customer-response-reactivation",
      "escalation-schedule-tuning",
      "knowledge-deflection-for-support",
      "multi-step-request-approvals",
      "persona-based-form-redesign",
      "pilot-based-patch-rollout",
      "problem-review-and-corrective-action",
      "quick-action-notification-pack",
      "relationship-driven-task-model",
      "scheduled-report-push-to-external-endpoint",
      "validation-guardrail-rollout",
      "weekly-open-incident-summary",
      "workspace-first-call-resolution",
      "workspace-shift-left-triage"
    ],
    "trickyIds": [
      "dashboard-vs-report",
      "escalation-vs-notification",
      "incident-vs-service-request",
      "lookup-vs-parent-child-relationship",
      "object-extension-vs-new-object",
      "quick-action-vs-workflow",
      "saved-search-vs-dashboard",
      "single-form-vs-role-specific-layouts",
      "template-content-vs-recipient-logic",
      "ui-required-vs-business-validation",
      "workflow-vs-state-driven-routing",
      "workspace-context-vs-ticket-notes",
      "workspace-vs-service-desk-notes"
    ],
    "priority": "Important",
    "whatInterviewersUsuallyAsk": [
      "What is a business object?",
      "Which KPIs matter?",
      "Why do email templates matter?",
      "How do you design a good form?",
      "When would you extend an object versus creating a separate one?",
      "How do you choose KPIs?"
    ],
    "answerFramework": [
      "Start with what the role owns day to day.",
      "Mention the highest-priority modules you would focus on first.",
      "Name the topics interviewers usually probe for this role.",
      "Close with one implementation example or support scenario."
    ],
    "studyOrder": [
      "Core topics first",
      "Then coding or automation questions",
      "Then use cases",
      "Finish with tricky distinctions and quiz review"
    ]
  },
  {
    "id": "ivanti-velocity-consultant",
    "name": "Ivanti Velocity Consultant",
    "group": "Frontline",
    "summary": "Designs browser- and scan-optimized frontline workflows for warehouse and field teams.",
    "moduleIds": [
      "ivanti-velocity",
      "ivanti-neurons-platform"
    ],
    "skills": [
      "frontline UX",
      "workflow simplification",
      "scan-first design",
      "change adoption",
      "operational efficiency"
    ],
    "topicIds": [
      "scan-first-workflow-design",
      "velocity-browser-sessions"
    ],
    "codingIds": [
      "velocity-flow-redesign",
      "velocity-session-optimization"
    ],
    "useCaseIds": [
      "platform-cross-workflow-automation",
      "velocity-web-modernization",
      "warehouse-picking-redesign"
    ],
    "trickyIds": [
      "scan-speed-vs-data-quality",
      "velocity-modernize-vs-replace"
    ],
    "priority": "Advanced",
    "whatInterviewersUsuallyAsk": [
      "What makes a good scan workflow?",
      "What is a Velocity browser session?",
      "How do you simplify a warehouse workflow?",
      "What makes a session redesign successful?",
      "Explain the difference in scan speed vs data quality in frontline flows.",
      "Explain the difference in velocity modernization vs full app replacement."
    ],
    "answerFramework": [
      "Start with what the role owns day to day.",
      "Mention the highest-priority modules you would focus on first.",
      "Name the topics interviewers usually probe for this role.",
      "Close with one implementation example or support scenario."
    ],
    "studyOrder": [
      "Core topics first",
      "Then coding or automation questions",
      "Then use cases",
      "Finish with tricky distinctions and quiz review"
    ]
  }
]